configloader/__init__.py
configloader/configloader.py
mfc_config_loader-0.0.5.dist-info/LICENSE
mfc_config_loader-0.0.5.dist-info/METADATA
mfc_config_loader-0.0.5.dist-info/WHEEL
mfc_config_loader-0.0.5.dist-info/top_level.txt
mfc_config_loader-0.0.5.dist-info/RECORD
