Metadata-Version: 2.1
Name: mfc-config-loader
Version: 0.0.5
Summary: Streamlines access and management of YAML-based configurations
Author-email: Vitaliy Gogolev <vitaliy@gogolevs.com>
License: MIT License
Project-URL: Repository, https://github.com/vgogolev/mfc-config-loader.git
Keywords: config,config loader,config manager
Classifier: Development Status :: 3 - Alpha
Classifier: Intended Audience :: Developers
Classifier: Programming Language :: Python
Requires-Python: >=3.8
License-File: LICENSE
Requires-Dist: black ==23.3.0
Requires-Dist: pylint ==2.17.3
Requires-Dist: pytest ~=7.3.1
Requires-Dist: flake8 ==6.0.0
Requires-Dist: coverage ==7.2.3
Requires-Dist: pre-commit ==3.2.2
Requires-Dist: PyYAML ~=6.0
Requires-Dist: setuptools >=66.0.0
